bondzai.bootstrap_framework-0.0.34-py3.10-nspkg.pth
bondzai/bootstrap_framework/__init__.py
bondzai/bootstrap_framework/bootstrap.py
bondzai/bootstrap_framework/dvs_agent.py
bondzai/bootstrap_framework/dvs_com.py
bondzai/bootstrap_framework/dvs_config.py
bondzai/bootstrap_framework/file_handler.py
bondzai/bootstrap_framework/logger.py
bondzai/bootstrap_framework/self_test.py
bondzai.bootstrap_framework-0.0.34.dist-info/METADATA
bondzai.bootstrap_framework-0.0.34.dist-info/NOTICE
bondzai.bootstrap_framework-0.0.34.dist-info/WHEEL
bondzai.bootstrap_framework-0.0.34.dist-info/namespace_packages.txt
bondzai.bootstrap_framework-0.0.34.dist-info/top_level.txt
bondzai.bootstrap_framework-0.0.34.dist-info/zip-safe
bondzai.bootstrap_framework-0.0.34.dist-info/RECORD
