Metadata-Version: 2.1
Name: bondzai.bootstrap-framework
Version: 0.0.34
Summary: Bondzai Bootstrap Framework
Home-page: UNKNOWN
Author: Bondzai
License: Apache License 2.0
Keywords: davinsy,bondzai
Platform: UNKNOWN
Classifier: Programming Language :: Python :: 3
Classifier: License :: OSI Approved :: Apache Software License
Classifier: Operating System :: OS Independent
License-File: NOTICE
Requires-Dist: bondzai.davinsy-py (==0.0.19)
Requires-Dist: numpy (<2.0.0,>=1.25)
Requires-Dist: pyyaml (==6.0)
